{
  "api_name": "docker-hub",
  "novelty_score": 0,
  "alternatives": null,
  "gaps": null,
  "patterns": null,
  "recommendation": "",
  "researched_at": "0001-01-01T00:00:00Z",
  "novel_features": [
    {
      "name": "Repository discovery",
      "command": "search",
      "description": "Search Docker Hub repositories with agent-ready JSON, compact output, and live/local source controls.",
      "rationale": ""
    },
    {
      "name": "Repository details",
      "command": "repositories",
      "description": "Inspect repository metadata and tags from one CLI surface for image selection and automation.",
      "rationale": ""
    },
    {
      "name": "Offline archive workflow",
      "command": "workflow archive",
      "description": "Sync Docker Hub resources into the local store so agents can search and analyze without repeated live calls.",
      "rationale": ""
    }
  ],
  "novel_features_built": [
    {
      "name": "Repository discovery",
      "command": "search",
      "description": "Search Docker Hub repositories with agent-ready JSON, compact output, and live/local source controls.",
      "rationale": ""
    },
    {
      "name": "Repository details",
      "command": "repositories",
      "description": "Inspect repository metadata and tags from one CLI surface for image selection and automation.",
      "rationale": ""
    },
    {
      "name": "Offline archive workflow",
      "command": "workflow archive",
      "description": "Sync Docker Hub resources into the local store so agents can search and analyze without repeated live calls.",
      "rationale": ""
    }
  ]
}